test_pkg_zteinck/__init__.py
test_pkg_zteinck/main.py
test_pkg_zteinck/newtest.py
test_pkg_zteinck-1.1.1.dist-info/METADATA
test_pkg_zteinck-1.1.1.dist-info/WHEEL
test_pkg_zteinck-1.1.1.dist-info/RECORD
