Metadata-Version: 2.1
Name: test-pkg-zteinck
Version: 1.1.1
Summary: 
Author: Your Name
Author-email: you@example.com
Requires-Python: >=3.11,<4.0
Classifier: Programming Language :: Python :: 3
Classifier: Programming Language :: Python :: 3.11
Classifier: Programming Language :: Python :: 3.12
Requires-Dist: iterlab (>=0.1.0,<0.2.0)
